reversed_name/__init__.py
reversed_name/reversed_name.py
reversed_name-0.0.1.dist-info/LICENSE
reversed_name-0.0.1.dist-info/METADATA
reversed_name-0.0.1.dist-info/WHEEL
reversed_name-0.0.1.dist-info/top_level.txt
reversed_name-0.0.1.dist-info/RECORD
