Metadata-Version: 2.1
Name: reversed-name
Version: 0.0.1
Summary: UNKNOWN
Home-page: UNKNOWN
Author: SangDoo Nam
License: UNKNOWN
Platform: UNKNOWN
Classifier: Programming Language :: Python :: 3
Classifier: License :: OSI Approved :: MIT License
Classifier: Operating System :: OS Independent
Requires-Python: >=3.6
License-File: LICENSE
